proper_cli/__init__.py
proper_cli/helpers.py
proper_cli/main.py
proper_cli/parser.py
proper_cli/pastel/__init__.py
proper_cli/pastel/pastel.py
proper_cli/pastel/stack.py
proper_cli/pastel/style.py
proper_cli/py.typed
proper_cli-1.4.1.dist-info/METADATA
proper_cli-1.4.1.dist-info/WHEEL
proper_cli-1.4.1.dist-info/RECORD
