Metadata-Version: 2.1
Name: proper-cli
Version: 1.4.1
Summary: Replace your HTML templates with Python server-Side components
Home-page: https://github.com/jpsca/proper-cli
License: MIT
Author: Juan-Pablo Scaletti
Author-email: juanpablo@jpscaletti.com
Requires-Python: >=3.9,<4.0
Classifier: Development Status :: 4 - Beta
Classifier: Environment :: Web Environment
Classifier: Intended Audience :: Developers
Classifier: License :: OSI Approved :: MIT License
Classifier: Programming Language :: Python :: 3
Classifier: Programming Language :: Python :: 3.9
Classifier: Programming Language :: Python :: 3.10
Classifier: Programming Language :: Python :: 3.11
Classifier: Programming Language :: Python :: 3.12
Classifier: Programming Language :: Python :: 3 :: Only
Classifier: Topic :: Software Development :: Libraries
Classifier: Topic :: Software Development :: Libraries :: Python Modules
Classifier: Topic :: Software Development :: User Interfaces
Classifier: Typing :: Typed
Project-URL: Repository, https://github.com/jpsca/proper-cli
